PyCharacterAI/__init__.py
PyCharacterAI/chat.py
PyCharacterAI/client.py
PyCharacterAI/message.py
PyCharacterAI/requester.py
PyCharacterAI_delete_image_format-1.0.1.dist-info/LICENSE
PyCharacterAI_delete_image_format-1.0.1.dist-info/METADATA
PyCharacterAI_delete_image_format-1.0.1.dist-info/WHEEL
PyCharacterAI_delete_image_format-1.0.1.dist-info/top_level.txt
PyCharacterAI_delete_image_format-1.0.1.dist-info/RECORD
