Metadata-Version: 2.1
Name: PyCharacterAI-delete-image-format
Version: 1.0.1
Summary: An unofficial asynchronous api wrapper for Character AI
Home-page: https://github.com/Xtr4F/PyCharacterAI
Author: XtraF
Author-email: igoromarov15@gmail.com
Classifier: Programming Language :: Python :: 3.10
Classifier: License :: OSI Approved :: MIT License
Requires-Python: >=3.7
License-File: LICENSE
Requires-Dist: playwright >=1.35.0
Requires-Dist: uuid >=1.30
Requires-Dist: requests
